bblab/__main__.py
bblab-1.0.0.dist-info/METADATA
bblab-1.0.0.dist-info/WHEEL
bblab-1.0.0.dist-info/licenses/LICENSE
bblab-1.0.0.dist-info/licenses/LICENSE.txt
bblab-1.0.0.dist-info/RECORD
