Metadata-Version: 2.4
Name: bblab
Version: 1.0.0
Summary: bblab - A namespace for BitByteLab libraries, tools, scripts, and utilities. It does not contain any functional logic beyond branding and identification; created only to reserve the `bblab` name as a namespace package.  It allows future submodules like bblab.cli, bblab.utils, bblab.ai and others to coexist under a unified namespace in the BitByteLab ecosystem, following modern Python packaging practices.
Project-URL: Homepage, https://bitbytelab.github.io/
Project-URL: BitByteLab, https://github.com/bitbytelab
Project-URL: PyPI, https://pypi.org/project/bblab/
Project-URL: Author-GitHub, https://github.com/rsmahmud
Project-URL: Author-LinkedIn, https://www.linkedin.com/in/rsmahmud
Project-URL: Author-Portfolio, https://rsmahmud.github.io/
Author-email: Hasan Rasel <rrss.mahmud@gmail.com>
Maintainer-email: Hasan Rasel <rrss.mahmud@gmail.com>
License-Expression: MIT
License-File: LICENSE
License-File: LICENSE.txt
Keywords: bblab,bitbytelab,namespace package
Classifier: License :: OSI Approved :: MIT License
Classifier: Operating System :: OS Independent
Classifier: Programming Language :: Python :: 3
Classifier: Topic :: Software Development :: Libraries :: Python Modules
Requires-Python: >=3.10
